[{"imdb_id": "nm2138653", "Name": "Deepika Padukone"}, {"imdb_id": "nm0451234", "Name": "Irrfan Khan"}, {"imdb_id": "nm0944834", "Name": "Raghuvir Yadav"}, {"imdb_id": "nm7464979", "Name": "Balendar Singh"}, {"imdb_id": "nm7602180", "Name": "Sajal Bhattacharya"}, {"imdb_id": "nm7602182", "Name": "Nutan Mathur"}, {"imdb_id": "nm7602183", "Name": "Aniruddha Roy Chowdhury"}, {"imdb_id": "nm0244865", "Name": "Avijit Dutt"}, {"imdb_id": "nm0000821", "Name": "Amitabh Bachchan"}, {"imdb_id": "nm0154139", "Name": "Moushumi Chatterjee"}, {"imdb_id": "nm1702868", "Name": "Jishu Sengupta"}, {"imdb_id": "nm5000540", "Name": "Swaroopa Ghosh"}, {"imdb_id": "nm7602181", "Name": "Rupsa Banerjee"}, {"imdb_id": "nm4114810", "Name": "Prerna Chawla"}, {"imdb_id": "nm0154119", "Name": "Bishwadeep Chatterjee"}]